irish_property/__init__.py
irish_property/constants.py
irish_property/daft_listing.py
irish_property/listing.py
irish_property/log.py
irish_property/myhome_cli.py
irish_property/property_ie_cli.py
irish_property/settings.py
irish_property/utils.py
irish_property/bin/__init__.py
irish_property/bin/configure.py
irish_property/bin/find.py
irish_property/bin/remove_persistence.py
irish_property/bin/run_notify.py
irish_property-0.0.2.dist-info/LICENSE
irish_property-0.0.2.dist-info/METADATA
irish_property-0.0.2.dist-info/WHEEL
irish_property-0.0.2.dist-info/entry_points.txt
irish_property-0.0.2.dist-info/top_level.txt
irish_property-0.0.2.dist-info/RECORD
